[{"model": "movies.actor", "pk": 62, "fields": {"name": "Bruce Willis", "profile_path": "/caX3KtMU42EP3VLRFFBwqIIrch5.jpg"}}, {"model": "movies.actor", "pk": 131, "fields": {"name": "Jake Gyllenhaal", "profile_path": "/oA6fp6SQBQQWZEzn4NfY3E8mJhV.jpg"}}, {"model": "movies.actor", "pk": 133, "fields": {"name": "Peter Sarsgaard", "profile_path": "/jOc4VjxPaOkWOqnLCxd8BJy9g5i.jpg"}}, {"model": "movies.actor", "pk": 134, "fields": {"name": "Jamie Foxx", "profile_path": "/hPwCMEq6jLAidsXAX5BfoYgIfg2.jpg"}}, {"model": "movies.actor", "pk": 206, "fields": {"name": "Jim Carrey", "profile_path": "/u0AqTz6Y7GHPCHINS01P7gPvDSb.jpg"}}, {"model": "movies.actor", "pk": 287, "fields": {"name": "Brad Pitt", "profile_path": "/oTB9vGIBacH5aQNS0pUM74QSWuf.jpg"}}, {"model": "movies.actor", "pk": 454, "fields": {"name": 